pip_mirror/__init__.py
pip_mirror/apache_reader.py
pip_mirror/apache_stats.py
pip_mirror/sqlite.py
pip_mirror-0.2.data/scripts/pip_mirror
pip_mirror-0.2.data/scripts/pip_mirror_check_files
pip_mirror-0.2.data/scripts/processlogs
pip_mirror-0.2.dist-info/DESCRIPTION.rst
pip_mirror-0.2.dist-info/METADATA
pip_mirror-0.2.dist-info/RECORD
pip_mirror-0.2.dist-info/WHEEL
pip_mirror-0.2.dist-info/metadata.json
pip_mirror-0.2.dist-info/top_level.txt
