Metadata-Version: 2.0
Name: pip-mirror
Version: 0.2
Summary: Mirroring tool that implements a local pip mirror via PyPi
Home-page: https://github.com/ianmaguire/pip_mirror
Author: Ian Maguire
Author-email: mr.scalability@gmail.com
License: Creative Commons version 4.0
Keywords: pip,mirror,pep381,bandersnatch
Platform: UNKNOWN
